EpubCrawler/__init__.py
EpubCrawler/__main__.py
EpubCrawler/common.py
EpubCrawler/config.py
EpubCrawler/img.py
EpubCrawler/sele_crawler.py
EpubCrawler/util.py
EpubCrawler-2023.7.9.2.dist-info/LICENSE
EpubCrawler-2023.7.9.2.dist-info/METADATA
EpubCrawler-2023.7.9.2.dist-info/WHEEL
EpubCrawler-2023.7.9.2.dist-info/entry_points.txt
EpubCrawler-2023.7.9.2.dist-info/top_level.txt
EpubCrawler-2023.7.9.2.dist-info/RECORD
