Metadata-Version: 2.1
Name: EpubCrawler
Version: 2023.7.9.2
Summary: EpubCrawler，用于抓取网页内容并制作 EPUB 的小工具
Home-page: https://github.com/apachecn/epub-crawler
Author: wizardforcel
Author-email: wizard.z@qq.com
Keywords: ebook,epub,crawler,爬虫,电子书
Classifier: Development Status :: 4 - Beta
Classifier: Environment :: Console
Classifier: Intended Audience :: Developers
Classifier: Intended Audience :: End Users/Desktop
Classifier: License :: Other/Proprietary License
Classifier: Natural Language :: Chinese (Simplified)
Classifier: Natural Language :: English
Classifier: Operating System :: OS Independent
Classifier: Programming Language :: Python :: 3
Classifier: Programming Language :: Python :: 3 :: Only
Classifier: Programming Language :: Python :: 3.6
Classifier: Programming Language :: Python :: 3.7
Classifier: Topic :: Internet :: WWW/HTTP
Classifier: Topic :: Text Processing :: Markup :: HTML
Classifier: Topic :: Utilities
Requires-Python: >=3.6
License-File: LICENSE
Requires-Dist: requests[socks]
Requires-Dist: pyquery
Requires-Dist: GenEpub
Requires-Dist: imgyaso
Requires-Dist: readability-lxml
Requires-Dist: selenium
Requires-Dist: pyyaml
